[
  {
    "aptDong": " ",
    "aptNm": "우리",
    "aptSeq": "46780-9",
    "bonbun": "0451",
    "bubun": "0000",
    "buildYear": "1992",
    "buyerGbn": "개인",
    "cdealDay": " ",
    "cdealType": " ",
    "dealAmount": "10,000",
    "dealDay": "3",
    "dealMonth": "1",
    "dealYear": "2025",
    "dealingGbn": "직거래",
    "estateAgentSggNm": " ",
    "excluUseAr": "84.86",
    "floor": "5",
    "jibun": "451",
    "landCd": "1",
    "landLeaseholdGbn": "N",
    "rgstDate": " ",
    "roadNm": "신정길",
    "roadNmBonbun": "00047",
    "roadNmBubun": "00024",
    "roadNmCd": "4670251",
    "roadNmSeq": "01",
    "roadNmSggCd": "46780",
    "roadNmbCd": "0",
    "sggCd": "46780",
    "slerGbn": "개인",
    "umdCd": "25338",
    "umdNm": "벌교읍 회정리"
  },
  {
    "aptDong": "제103",
    "aptNm": "우산주공",
    "aptSeq": "46780-12",
    "bonbun": "0631",
    "bubun": "0001",
    "buildYear": "1999",
    "buyerGbn": "개인",
    "cdealDay": " ",
    "cdealType": " ",
    "dealAmount": "11,800",
    "dealDay": "12",
    "dealMonth": "1",
    "dealYear": "2025",
    "dealingGbn": "중개거래",
    "estateAgentSggNm": "전남 보성군",
    "excluUseAr": "49.85",
    "floor": "11",
    "jibun": "631-1",
    "landCd": "1",
    "landLeaseholdGbn": "N",
    "rgstDate": "25.02.06",
    "roadNm": "중앙로",
    "roadNmBonbun": "00007",
    "roadNmBubun": "00000",
    "roadNmCd": "3290018",
    "roadNmSeq": "01",
    "roadNmSggCd": "46780",
    "roadNmbCd": "0",
    "sggCd": "46780",
    "slerGbn": "개인",
    "umdCd": "25022",
    "umdNm": "보성읍 우산리"
  },
  {
    "aptDong": " ",
    "aptNm": "우산주공",
    "aptSeq": "46780-12",
    "bonbun": "0631",
    "bubun": "0001",
    "buildYear": "1999",
    "buyerGbn": "개인",
    "cdealDay": " ",
    "cdealType": " ",
    "dealAmount": "11,750",
    "dealDay": "7",
    "dealMonth": "1",
    "dealYear": "2025",
    "dealingGbn": "중개거래",
    "estateAgentSggNm": "전남 보성군",
    "excluUseAr": "59.89",
    "floor": "9",
    "jibun": "631-1",
    "landCd": "1",
    "landLeaseholdGbn": "N",
    "rgstDate": " ",
    "roadNm": "중앙로",
    "roadNmBonbun": "00007",
    "roadNmBubun": "00000",
    "roadNmCd": "3290018",
    "roadNmSeq": "01",
    "roadNmSggCd": "46780",
    "roadNmbCd": "0",
    "sggCd": "46780",
    "slerGbn": "개인",
    "umdCd": "25022",
    "umdNm": "보성읍 우산리"
  },
  {
    "aptDong": "B",
    "aptNm": "남일",
    "aptSeq": "46780-4",
    "bonbun": "0005",
    "bubun": "0011",
    "buildYear": "1991",
    "buyerGbn": "개인",
    "cdealDay": " ",
    "cdealType": " ",
    "dealAmount": "6,400",
    "dealDay": "3",
    "dealMonth": "1",
    "dealYear": "2025",
    "dealingGbn": "중개거래",
    "estateAgentSggNm": "전남 보성군",
    "excluUseAr": "59.78",
    "floor": "1",
    "jibun": "5-11",
    "landCd": "1",
    "landLeaseholdGbn": "N",
    "rgstDate": "25.01.15",
    "roadNm": "현충로",
    "roadNmBonbun": "00016",
    "roadNmBubun": "00008",
    "roadNmCd": "3290014",
    "roadNmSeq": "01",
    "roadNmSggCd": "46780",
    "roadNmbCd": "0",
    "sggCd": "46780",
    "slerGbn": "개인",
    "umdCd": "25028",
    "umdNm": "보성읍 원봉리"
  }
]